roodmus/__init__.py
roodmus/cli.py
roodmus/analysis/__init__.py
roodmus/analysis/analyse_alignment.py
roodmus/analysis/extract_particles.py
roodmus/analysis/plot_alignment.py
roodmus/analysis/plot_classes.py
roodmus/analysis/plot_ctf.py
roodmus/analysis/plot_frames.py
roodmus/analysis/plot_picking.py
roodmus/analysis/utils.py
roodmus/heterogeneity/__init__.py
roodmus/heterogeneity/hetRec.py
roodmus/heterogeneity/het_ensemblecomparison.py
roodmus/heterogeneity/het_metrics.py
roodmus/heterogeneity/latent_clustering.py
roodmus/heterogeneity/plot_heterogeneous_reconstruction.py
roodmus/heterogeneity/remove_hydrogens.py
roodmus/simulation/__init__.py
roodmus/simulation/configuration.py
roodmus/simulation/orientation_generator.py
roodmus/simulation/run_parakeet.py
roodmus/simulation/write_starfile.py
roodmus/trajectory/__init__.py
roodmus/trajectory/conformations_sampling.py
roodmus-0.0.35.dist-info/LICENSE
roodmus-0.0.35.dist-info/METADATA
roodmus-0.0.35.dist-info/WHEEL
roodmus-0.0.35.dist-info/entry_points.txt
roodmus-0.0.35.dist-info/top_level.txt
roodmus-0.0.35.dist-info/RECORD
