Metadata-Version: 2.1
Name: roodmus
Version: 0.0.35
Summary: Synthetic SP micrograph creation and analysis
Author-email: Joel Greer <joel.greer@stfc.ac.uk>, Maarten Joosten <m.j.joosten@tudelft.nl>
License: GNU GENERAL PUBLIC LICENSE
Project-URL: Homepage, https://github.com/ccpem/roodmus
Project-URL: Bug Tracker, https://github.com/ccpem/roodmus/issues
Keywords: parakeet,cryo-em,micrographs,analysis,roodmus,single-particle
Classifier: Programming Language :: Python :: 3
Classifier: Operating System :: OS Independent
Requires-Python: >=3.10
License-File: LICENSE
Requires-Dist: lxml-html-clean
Requires-Dist: mdtraj
Requires-Dist: glob2
Requires-Dist: seaborn
Requires-Dist: MDAnalysis
Requires-Dist: umap-learn
Requires-Dist: scikit-learn >=1.3
Requires-Dist: python-parakeet ==0.5.1
